juham_automation/__init__.py
juham_automation/japp.py
juham_automation/py.typed
juham_automation/automation/__init__.py
juham_automation/automation/energybalancer.py
juham_automation/automation/energycostcalculator.py
juham_automation/automation/heatingoptimizer.py
juham_automation/automation/leakdetector.py
juham_automation/automation/watercirculator.py
juham_automation/ts/__init__.py
juham_automation/ts/electricityprice_ts.py
juham_automation/ts/energybalancer_ts.py
juham_automation/ts/energycostcalculator_ts.py
juham_automation/ts/forecast_ts.py
juham_automation/ts/log_ts.py
juham_automation/ts/power_ts.py
juham_automation/ts/powermeter_ts.py
juham_automation/ts/powerplan_ts.py
juham_automation-0.2.23.dist-info/licenses/LICENSE.rst
juham_automation-0.2.23.dist-info/METADATA
juham_automation-0.2.23.dist-info/WHEEL
juham_automation-0.2.23.dist-info/entry_points.txt
juham_automation-0.2.23.dist-info/top_level.txt
juham_automation-0.2.23.dist-info/RECORD
