Metadata-Version: 2.4
Name: juham-automation
Version: 0.2.23
Summary: Juha's Ultimate Home Automation Masterpiece
Author-email: J Meskanen <juham.api@gmail.com>
Maintainer-email: "J. Meskanen" <juham.api@gmail.com>
License-Expression: MIT
Project-URL: Homepage, https://gitlab.com/juham/juham/juham-automation
Project-URL: Bug Reports, https://gitlab.com/juham/juham/juham-automationt
Project-URL: Funding, https://meskanen.com
Project-URL: Say Thanks!, http://meskanen.com
Project-URL: Source, https://gitlab.com/juham/juham/juham-automation
Keywords: home,automation,juham
Classifier: Development Status :: 4 - Beta
Classifier: Intended Audience :: Developers
Classifier: Topic :: Software Development
Classifier: Programming Language :: Python :: 3.8
Requires-Python: >=3.8
License-File: LICENSE.rst
Requires-Dist: juham_core>=0.2.6
Provides-Extra: dev
Requires-Dist: check-manifest; extra == "dev"
Requires-Dist: coverage>=7.0; extra == "dev"
Dynamic: license-file
